odoo/addons/sale_resource_booking/README.rst
odoo/addons/sale_resource_booking/__init__.py
odoo/addons/sale_resource_booking/__manifest__.py
odoo/addons/sale_resource_booking/i18n/es.po
odoo/addons/sale_resource_booking/i18n/fr.po
odoo/addons/sale_resource_booking/i18n/fr_CH.po
odoo/addons/sale_resource_booking/i18n/sale_resource_booking.pot
odoo/addons/sale_resource_booking/models/__init__.py
odoo/addons/sale_resource_booking/models/product_template.py
odoo/addons/sale_resource_booking/models/resource_booking.py
odoo/addons/sale_resource_booking/models/resource_booking_type.py
odoo/addons/sale_resource_booking/models/sale_order.py
odoo/addons/sale_resource_booking/models/sale_order_line.py
odoo/addons/sale_resource_booking/readme/CONFIGURE.rst
odoo/addons/sale_resource_booking/readme/CONTRIBUTORS.rst
odoo/addons/sale_resource_booking/readme/DESCRIPTION.rst
odoo/addons/sale_resource_booking/readme/INSTALL.rst
odoo/addons/sale_resource_booking/readme/USAGE.rst
odoo/addons/sale_resource_booking/static/description/icon.png
odoo/addons/sale_resource_booking/static/description/index.html
odoo/addons/sale_resource_booking/tests/__init__.py
odoo/addons/sale_resource_booking/tests/test_sale_resource_booking.py
odoo/addons/sale_resource_booking/views/product_template_views.xml
odoo/addons/sale_resource_booking/views/resource_booking_type_views.xml
odoo/addons/sale_resource_booking/views/resource_booking_views.xml
odoo/addons/sale_resource_booking/views/sale_order_views.xml
odoo/addons/sale_resource_booking/wizards/__init__.py
odoo/addons/sale_resource_booking/wizards/resource_booking_sale.py
odoo/addons/sale_resource_booking/wizards/resource_booking_sale_views.xml
odoo/addons/sale_resource_booking/wizards/sale_order_booking_confirm.py
odoo/addons/sale_resource_booking/wizards/sale_order_booking_confirm_views.xml
odoo12_addon_sale_resource_booking-12.0.1.0.1.dist-info/METADATA
odoo12_addon_sale_resource_booking-12.0.1.0.1.dist-info/WHEEL
odoo12_addon_sale_resource_booking-12.0.1.0.1.dist-info/top_level.txt
odoo12_addon_sale_resource_booking-12.0.1.0.1.dist-info/RECORD
